blueprint/__init__.py
blueprint/builder.py
blueprint/config.py
blueprint/context.py
blueprint/run.py
blueprint/ml/__init__.py
blueprint/ml/dataprocessor.py
blueprint/ml/dataset.py
blueprint/ml/distributed.py
blueprint/ml/ema_config.py
blueprint/ml/inference.py
blueprint/ml/logger.py
blueprint/ml/optimizer.py
blueprint/ml/sampler.py
blueprint/ml/scorer.py
blueprint/ml/stats.py
blueprint/ml/storage.py
blueprint/ml/task.py
blueprint/ml/tester.py
blueprint/ml/trainer.py
blueprint/ml/util.py
blueprint/ml/viz.py
blueprint/ml/augmenters/__init__.py
blueprint/ml/augmenters/basic.py
blueprint/ml/augmenters/face.py
blueprint/ml/augmenters/image.py
blueprint/ml/augmenters/transform.py
py_blueprint-0.0.1.post3.dist-info/LICENSE
py_blueprint-0.0.1.post3.dist-info/METADATA
py_blueprint-0.0.1.post3.dist-info/WHEEL
py_blueprint-0.0.1.post3.dist-info/top_level.txt
py_blueprint-0.0.1.post3.dist-info/RECORD
