Metadata-Version: 2.1
Name: py-blueprint
Version: 0.0.1.post3
Summary: Configure Python to Yaml.
Home-page: https://github.com/YANG-H/BluePrint.git
Author: Hao Yang
Author-email: yanghao.alexis@foxmail.com
License: MIT
Platform: UNKNOWN
Requires-Python: >=3.7
License-File: LICENSE
Requires-Dist: torch
Requires-Dist: tqdm
Requires-Dist: pyyaml
Requires-Dist: numpy
Requires-Dist: matplotlib
Requires-Dist: scikit-image
Requires-Dist: scikit-learn
Requires-Dist: opencv-python
Requires-Dist: timm
Requires-Dist: xmltodict
Requires-Dist: tensorboard
